pysp/__init__.py
pysp/sbasic.py
pysp/sconf.py
pysp/scsv.py
pysp/serror.py
pysp/sjson.py
pysp/ssql.py
pysp-0.0.10.data/data/VERSION
pysp-0.0.10.dist-info/LICENSE
pysp-0.0.10.dist-info/METADATA
pysp-0.0.10.dist-info/WHEEL
pysp-0.0.10.dist-info/top_level.txt
pysp-0.0.10.dist-info/RECORD
