Metadata-Version: 2.1
Name: pysp
Version: 0.0.10
Summary: Python-Support-Package
Home-page: https://github.com/peanutstars/py-support-package
Author: HyunSuk Lee
Author-email: peanutstars.job@gmail.com
License: UNKNOWN
Keywords: yaml configuration
Platform: UNKNOWN
Classifier: Environment :: Console
Classifier: Intended Audience :: Developers
Classifier: Operating System :: POSIX :: Linux
Classifier: Topic :: System :: Operating System Kernels :: Linux
Classifier: Programming Language :: Python :: 3
Classifier: Programming Language :: Python :: 3.6
Requires-Dist: PyYAML (>=3.12)
Requires-Dist: SQLAlchemy (>=1.2.14)
